LICENSE
VERSION
requirements.txt
osfclient/__init__.py
osfclient/__main__.py
osfclient/__version__.py
osfclient/api.py
osfclient/cli.py
osfclient/exceptions.py
osfclient/utils.py
osfclient/models/__init__.py
osfclient/models/core.py
osfclient/models/file.py
osfclient/models/project.py
osfclient/models/session.py
osfclient/models/storage.py
osfclient/tests/__init__.py
osfclient/tests/fake_responses.py
osfclient/tests/mocks.py
osfclient/tests/test_api.py
osfclient/tests/test_cli.py
osfclient/tests/test_cloning.py
osfclient/tests/test_fetching.py
osfclient/tests/test_file.py
osfclient/tests/test_geturling.py
osfclient/tests/test_listing.py
osfclient/tests/test_main.py
osfclient/tests/test_project.py
osfclient/tests/test_removing.py
osfclient/tests/test_session.py
osfclient/tests/test_storage.py
osfclient/tests/test_uploading.py
osfclient/tests/test_utils.py
osfclient-0.0.5.dist-info/LICENSE
osfclient-0.0.5.dist-info/METADATA
osfclient-0.0.5.dist-info/WHEEL
osfclient-0.0.5.dist-info/entry_points.txt
osfclient-0.0.5.dist-info/top_level.txt
osfclient-0.0.5.dist-info/RECORD
